fluxional/__init__.py
fluxional/__main__.py
fluxional/cli/__init__.py
fluxional/core/__init__.py
fluxional/core/app.py
fluxional/core/core.py
fluxional/core/events.py
fluxional/core/handlers.py
fluxional/core/infrastructure/__init__.py
fluxional/core/infrastructure/base.py
fluxional/core/infrastructure/cdk.py
fluxional/core/infrastructure/resources.py
fluxional/core/infrastructure/types.py
fluxional/core/logic.py
fluxional/core/settings.py
fluxional/core/tools.py
fluxional/core/types.py
fluxional/deployment/__init__.py
fluxional/deployment/constants.py
fluxional/deployment/engine.py
fluxional/deployment/exceptions.py
fluxional/deployment/utils.py
fluxional/dev/__init__.py
fluxional/dev/client.py
fluxional/dev/runner.py
fluxional/exceptions.py
fluxional/py.typed
fluxional/types.py
fluxional/utils.py
fluxional-0.1.11.dist-info/LICENSE
fluxional-0.1.11.dist-info/METADATA
fluxional-0.1.11.dist-info/WHEEL
fluxional-0.1.11.dist-info/entry_points.txt
fluxional-0.1.11.dist-info/RECORD
