Metadata-Version: 2.1
Name: fluxional
Version: 0.1.11
Summary: 
License: MIT
Author: fluxional
Requires-Python: >=3.10,<4.0
Classifier: License :: OSI Approved :: MIT License
Classifier: Programming Language :: Python :: 3
Classifier: Programming Language :: Python :: 3.10
Classifier: Programming Language :: Python :: 3.11
Classifier: Programming Language :: Python :: 3.12
Provides-Extra: all
Provides-Extra: dev
Requires-Dist: aws-cdk-aws-apigatewayv2-integrations-alpha (==2.114.1a0) ; extra == "all"
Requires-Dist: aws-cdk-lib (==2.114.1) ; extra == "all"
Requires-Dist: awscrt (>=0.20.0,<0.21.0) ; extra == "all" or extra == "dev"
Requires-Dist: awsiotsdk (>=1.20.0,<2.0.0) ; extra == "all" or extra == "dev"
Requires-Dist: boto3 (>=1.29.6,<2.0.0)
Requires-Dist: docker (==6.1.3)
Requires-Dist: python-dotenv (>=1.0.0,<2.0.0)
Requires-Dist: requests (==2.31.0)
Requires-Dist: rich (>=13.7.0,<14.0.0)
Requires-Dist: typer (>=0.9.0)
